zeep/__init__.py
zeep/__main__.py
zeep/cache.py
zeep/client.py
zeep/exceptions.py
zeep/helpers.py
zeep/loader.py
zeep/ns.py
zeep/plugins.py
zeep/proxy.py
zeep/py.typed
zeep/settings.py
zeep/transports.py
zeep/utils.py
zeep/wsa.py
zeep/wsdl/__init__.py
zeep/wsdl/attachments.py
zeep/wsdl/definitions.py
zeep/wsdl/parse.py
zeep/wsdl/utils.py
zeep/wsdl/wsdl.py
zeep/wsdl/bindings/__init__.py
zeep/wsdl/bindings/http.py
zeep/wsdl/bindings/soap.py
zeep/wsdl/messages/__init__.py
zeep/wsdl/messages/base.py
zeep/wsdl/messages/http.py
zeep/wsdl/messages/mime.py
zeep/wsdl/messages/multiref.py
zeep/wsdl/messages/soap.py
zeep/wsdl/messages/xop.py
zeep/wsse/__init__.py
zeep/wsse/compose.py
zeep/wsse/signature.py
zeep/wsse/username.py
zeep/wsse/utils.py
zeep/xsd/__init__.py
zeep/xsd/const.py
zeep/xsd/context.py
zeep/xsd/printer.py
zeep/xsd/schema.py
zeep/xsd/utils.py
zeep/xsd/valueobjects.py
zeep/xsd/visitor.py
zeep/xsd/elements/__init__.py
zeep/xsd/elements/any.py
zeep/xsd/elements/attribute.py
zeep/xsd/elements/base.py
zeep/xsd/elements/builtins.py
zeep/xsd/elements/element.py
zeep/xsd/elements/indicators.py
zeep/xsd/elements/references.py
zeep/xsd/types/__init__.py
zeep/xsd/types/any.py
zeep/xsd/types/base.py
zeep/xsd/types/builtins.py
zeep/xsd/types/collection.py
zeep/xsd/types/complex.py
zeep/xsd/types/simple.py
zeep/xsd/types/unresolved.py
zeep_bold-4.2.1.dist-info/LICENSE
zeep_bold-4.2.1.dist-info/METADATA
zeep_bold-4.2.1.dist-info/WHEEL
zeep_bold-4.2.1.dist-info/top_level.txt
zeep_bold-4.2.1.dist-info/RECORD
