Metadata-Version: 2.1
Name: zeep-bold
Version: 4.2.1
Summary: A fork of Michael van Tellingen of python-zeep
Home-page: https://github.com/jindriago-scf/python-zeep
Author: Julio Indriago
Author-email: julio.indriago@bold.co
License: MIT
Classifier: Development Status :: 5 - Production/Stable
Classifier: License :: OSI Approved :: MIT License
Classifier: Programming Language :: Python :: 3
Classifier: Programming Language :: Python :: 3 :: Only
Classifier: Programming Language :: Python :: 3.7
Classifier: Programming Language :: Python :: 3.8
Classifier: Programming Language :: Python :: 3.9
Classifier: Programming Language :: Python :: 3.10
Classifier: Programming Language :: Python :: 3.11
Classifier: Programming Language :: Python :: Implementation :: CPython
Classifier: Programming Language :: Python :: Implementation :: PyPy
Requires-Python: >=3.7
License-File: LICENSE
Requires-Dist: attrs >=17.2.0
Requires-Dist: isodate >=0.5.4
Requires-Dist: lxml >=4.6.0
Requires-Dist: platformdirs >=1.4.0
Requires-Dist: requests >=2.7.0
Requires-Dist: requests-toolbelt >=0.7.1
Requires-Dist: requests-file >=1.5.1
Requires-Dist: pytz
Requires-Dist: cached-property >=1.3.0 ; python_version < "3.8"
Provides-Extra: async
Requires-Dist: httpx >=0.15.0 ; extra == 'async'
Provides-Extra: docs
Requires-Dist: sphinx >=1.4.0 ; extra == 'docs'
Provides-Extra: test
Requires-Dist: coverage[toml] ==5.2.1 ; extra == 'test'
Requires-Dist: freezegun ==0.3.15 ; extra == 'test'
Requires-Dist: pretend ==1.0.9 ; extra == 'test'
Requires-Dist: pytest-cov ==2.8.1 ; extra == 'test'
Requires-Dist: pytest-httpx ; extra == 'test'
Requires-Dist: pytest-asyncio ; extra == 'test'
Requires-Dist: pytest ==6.2.5 ; extra == 'test'
Requires-Dist: requests-mock >=0.7.0 ; extra == 'test'
Requires-Dist: isort ==5.3.2 ; extra == 'test'
Requires-Dist: flake8 ==3.8.3 ; extra == 'test'
Requires-Dist: flake8-blind-except ==0.1.1 ; extra == 'test'
Requires-Dist: flake8-debugger ==3.2.1 ; extra == 'test'
Requires-Dist: flake8-imports ==0.1.1 ; extra == 'test'
Provides-Extra: xmlsec
Requires-Dist: xmlsec >=0.6.1 ; extra == 'xmlsec'
